Metadata-Version: 1.0
Name: py-geoinova-apiclient
Version: 1.6
Summary: Pacote responsável pela interação com a API da GeoInova
Home-page: UNKNOWN
Author: Manoel Neco Jr
Author-email: manoel.junior@geoinova.com.br
License: UNKNOWN
Platform: UNKNOWN
